{
  "recentFiles": [
    {
      "basename": "刷题笔记",
      "path": "Gre/刷题笔记.md"
    },
    {
      "basename": "错误选项特征",
      "path": "Gre/错误选项特征.md"
    },
    {
      "basename": "阅读题型",
      "path": "Gre/阅读题型.md"
    },
    {
      "basename": "主旨题",
      "path": "Gre/主旨题.md"
    },
    {
      "basename": "4. Obsidian中的链接",
      "path": "Obidian使用教程/4. Obsidian中的链接.pdf"
    },
    {
      "basename": "截屏2023-08-18 15.33.30",
      "path": "attachment/截屏2023-08-18 15.33.30.png"
    },
    {
      "basename": "2023-07-31",
      "path": "Daily/2023-07-31.md"
    },
    {
      "basename": "阅读刷题模版",
      "path": "Template/阅读刷题模版.md"
    },
    {
      "basename": "5. Obsidian使用技巧",
      "path": "Obidian使用教程/5. Obsidian使用技巧.pdf"
    },
    {
      "basename": "6. Obsidian插件（上）",
      "path": "Obidian使用教程/6. Obsidian插件（上）.pdf"
    },
    {
      "basename": "8. 搜索的技巧",
      "path": "Obidian使用教程/8. 搜索的技巧.pdf"
    },
    {
      "basename": "7. Obsidian插件（下）",
      "path": "Obidian使用教程/7. Obsidian插件（下）.pdf"
    },
    {
      "basename": "2. 使用Obsidian",
      "path": "Obidian使用教程/2. 使用Obsidian.pdf"
    },
    {
      "basename": "1. Obsidian简介",
      "path": "Obidian使用教程/1. Obsidian简介.pdf"
    },
    {
      "basename": "JavaSe",
      "path": "算法笔记/JavaSe.md"
    },
    {
      "basename": "算法体系笔记",
      "path": "算法笔记/算法体系笔记.md"
    },
    {
      "basename": "Waterfall Streams",
      "path": "算法笔记/zuoAlgorithm/200. ★算法题目汇总★/★算法面试题汇总/Waterfall Streams.md"
    },
    {
      "basename": "局部最小值问题",
      "path": "算法笔记/zuoAlgorithm/200. ★算法题目汇总★/★算法面试题汇总/局部最小值问题.md"
    },
    {
      "basename": "01 认识复杂度、对数器、二分法与异或运算",
      "path": "算法笔记/zuoAlgorithm/100. 算法课程/10. 基础课/01 认识复杂度、对数器、二分法与异或运算.md"
    },
    {
      "basename": "在一个有序数组中，找小于等于某个数最右侧的位置",
      "path": "算法笔记/zuoAlgorithm/200. ★算法题目汇总★/★算法面试题汇总/在一个有序数组中，找小于等于某个数最右侧的位置.md"
    },
    {
      "basename": "在一个有序数组中，找大于等于某个数最左侧的位置",
      "path": "算法笔记/zuoAlgorithm/200. ★算法题目汇总★/★算法面试题汇总/在一个有序数组中，找大于等于某个数最左侧的位置.md"
    },
    {
      "basename": "在一个有序数组中，找某个数是否存在",
      "path": "算法笔记/zuoAlgorithm/200. ★算法题目汇总★/★算法面试题汇总/在一个有序数组中，找某个数是否存在.md"
    },
    {
      "basename": "01 认识复杂度、对数器、二分法",
      "path": "算法笔记/zuoAlgorithm/100. 算法课程/01. 体系学习班/01 认识复杂度、对数器、二分法.md"
    },
    {
      "basename": "插入排序",
      "path": "算法笔记/zuoAlgorithm/010. 代码模板/插入排序.md"
    },
    {
      "basename": "冒泡排序",
      "path": "算法笔记/zuoAlgorithm/010. 代码模板/冒泡排序.md"
    },
    {
      "basename": "选择排序",
      "path": "算法笔记/zuoAlgorithm/010. 代码模板/选择排序.md"
    },
    {
      "basename": "__算法数据结构体系学习班",
      "path": "算法笔记/zuoAlgorithm/000. 学习大纲/__算法数据结构体系学习班.md"
    },
    {
      "basename": "08 trie、桶排序、排序总结",
      "path": "算法笔记/zuoAlgorithm/100. 算法课程/01. 体系学习班/08 trie、桶排序、排序总结.md"
    },
    {
      "basename": "Markdown语法相关",
      "path": "算法笔记/zuoAlgorithm/1000.Misc/Markdown语法相关.md"
    },
    {
      "basename": "Links",
      "path": "算法笔记/zuoAlgorithm/1000.Misc/Links.md"
    },
    {
      "basename": "CodeForce",
      "path": "算法笔记/zuoAlgorithm/1000.Misc/CodeForce.md"
    },
    {
      "basename": "Atcoder",
      "path": "算法笔记/zuoAlgorithm/1000.Misc/Atcoder.md"
    },
    {
      "basename": "缩略语",
      "path": "算法笔记/zuoAlgorithm/1000.Misc/缩略语.md"
    },
    {
      "basename": "算法学习相关网站",
      "path": "算法笔记/zuoAlgorithm/1000.Misc/算法学习相关网站.md"
    },
    {
      "basename": "竞赛及思维训练",
      "path": "算法笔记/zuoAlgorithm/1000.Misc/竞赛及思维训练.md"
    },
    {
      "basename": "01 位运算、算法是什么、简单排序",
      "path": "算法笔记/zuoAlgorithm/100. 算法课程/00. 新手班/01 位运算、算法是什么、简单排序.md"
    },
    {
      "basename": "_Python 语言速成+进阶",
      "path": "算法笔记/zuoAlgorithm/002. 知识点总结/00. 编程语言相关/_Python 语言速成+进阶.md"
    },
    {
      "basename": "_Java 语言速成+进阶",
      "path": "算法笔记/zuoAlgorithm/002. 知识点总结/00. 编程语言相关/_Java 语言速成+进阶.md"
    },
    {
      "basename": "_C++ 语言速成+进阶",
      "path": "算法笔记/zuoAlgorithm/002. 知识点总结/00. 编程语言相关/_C++ 语言速成+进阶.md"
    },
    {
      "basename": "二叉树的递归套路",
      "path": "算法笔记/zuoAlgorithm/004. 刷题经验总结/二叉树的递归套路.md"
    },
    {
      "basename": "并查集代码",
      "path": "算法笔记/zuoAlgorithm/010. 代码模板/并查集代码.md"
    },
    {
      "basename": "不使用加减乘除算符实现加减乘除(仅位运算)",
      "path": "算法笔记/zuoAlgorithm/010. 代码模板/不使用加减乘除算符实现加减乘除(仅位运算).md"
    },
    {
      "basename": "比较器",
      "path": "算法笔记/zuoAlgorithm/010. 代码模板/比较器.md"
    },
    {
      "basename": "贪心算法",
      "path": "算法笔记/zuoAlgorithm/002. 知识点总结/20. 算法知识点/贪心算法.md"
    },
    {
      "basename": "_贪心算法Memo",
      "path": "算法笔记/zuoAlgorithm/001. 难点重点照顾/_贪心算法Memo.md"
    },
    {
      "basename": "一句话背诵知识点",
      "path": "算法笔记/zuoAlgorithm/001. 难点重点照顾/00. 需要熟记的知识点/一句话背诵知识点.md"
    },
    {
      "basename": "基础知识点",
      "path": "算法笔记/zuoAlgorithm/001. 难点重点照顾/00. 需要熟记的知识点/基础知识点.md"
    },
    {
      "basename": "基础面试题",
      "path": "算法笔记/zuoAlgorithm/001. 难点重点照顾/00. 需要熟记的知识点/基础面试题.md"
    },
    {
      "basename": "高级知识点",
      "path": "算法笔记/zuoAlgorithm/001. 难点重点照顾/00. 需要熟记的知识点/高级知识点.md"
    }
  ],
  "omittedPaths": [],
  "maxLength": null,
  "openType": "tab"
}