{
  "main": {
    "id": "4c2ab6348949ac36",
    "type": "split",
    "children": [
      {
        "id": "7c68c152873a5aa8",
        "type": "tabs",
        "children": [
          {
            "id": "411ec4089745389d",
            "type": "leaf",
            "state": {
              "type": "markdown",
              "state": {
                "file": "Daily/2024-09-08.md",
                "mode": "source",
                "source": false
              }
            }
          }
        ]
      }
    ],
    "direction": "vertical"
  },
  "left": {
    "id": "ab635de604a5016e",
    "type": "split",
    "children": [
      {
        "id": "b080565a5bdc1ee0",
        "type": "tabs",
        "children": [
          {
            "id": "aa677b3dd1721ac9",
            "type": "leaf",
            "state": {
              "type": "search",
              "state": {
                "query": "",
                "matchingCase": true,
                "explainSearch": false,
                "collapseAll": false,
                "extraContext": false,
                "sortOrder": "alphabetical"
              }
            }
          },
          {
            "id": "ba6b4f22edd19ea3",
            "type": "leaf",
            "state": {
              "type": "recent-files",
              "state": {}
            }
          },
          {
            "id": "882d4af5d1d2771a",
            "type": "leaf",
            "state": {
              "type": "bookmarks",
              "state": {}
            }
          },
          {
            "id": "ab3df9bd0138c1ec",
            "type": "leaf",
            "state": {
              "type": "file-explorer",
              "state": {
                "sortOrder": "alphabetical"
              }
            }
          }
        ],
        "currentTab": 1
      }
    ],
    "direction": "horizontal",
    "width": 307.51103591918945,
    "collapsed": true
  },
  "right": {
    "id": "5a22bf979ae2ada9",
    "type": "split",
    "children": [
      {
        "id": "3615ad6956876181",
        "type": "tabs",
        "children": [
          {
            "id": "00fa95f1d3b9e16a",
            "type": "leaf",
            "state": {
              "type": "backlink",
              "state": {
                "file": "Daily/2024-09-08.md",
                "collapseAll": false,
                "extraContext": false,
                "sortOrder": "alphabetical",
                "showSearch": false,
                "searchQuery": "",
                "backlinkCollapsed": false,
                "unlinkedCollapsed": true
              }
            }
          },
          {
            "id": "2f87866ceffc520a",
            "type": "leaf",
            "state": {
              "type": "outgoing-link",
              "state": {
                "file": "Daily/2024-09-08.md",
                "linksCollapsed": false,
                "unlinkedCollapsed": true
              }
            }
          },
          {
            "id": "72b5f7755887e447",
            "type": "leaf",
            "state": {
              "type": "tag",
              "state": {
                "sortOrder": "frequency",
                "useHierarchy": true
              }
            }
          },
          {
            "id": "8e0842b46de0cea8",
            "type": "leaf",
            "state": {
              "type": "outline",
              "state": {
                "file": "Daily/2024-09-08.md"
              }
            }
          },
          {
            "id": "f25abefced0eaffc",
            "type": "leaf",
            "state": {
              "type": "calendar",
              "state": {}
            }
          },
          {
            "id": "063591399d144e1d",
            "type": "leaf",
            "state": {
              "type": "all-properties",
              "state": {
                "sortOrder": "frequency",
                "showSearch": false,
                "searchQuery": ""
              }
            }
          },
          {
            "id": "655ea57791de2dbf",
            "type": "leaf",
            "state": {
              "type": "advanced-tables-toolbar",
              "state": {}
            }
          }
        ],
        "currentTab": 4
      }
    ],
    "direction": "horizontal",
    "width": 239.5
  },
  "left-ribbon": {
    "hiddenItems": {
      "switcher:打开快速切换": false,
      "graph:查看关系图谱": false,
      "canvas:新建白板": false,
      "daily-notes:打开/创建今天的日记": false,
      "templates:插入模板": false,
      "command-palette:打开命令面板": false,
      "markdown-importer:打开 Markdown 格式转换器": false,
      "workspaces:管理工作区布局": false,
      "audio-recorder:开始/结束录音": false,
      "publish:发布更改": false,
      "obsidian-memos:Thino": false,
      "table-editor-obsidian:Advanced Tables Toolbar": false,
      "obsidian-excalidraw-plugin:新建绘图文件": false
    }
  },
  "active": "411ec4089745389d",
  "lastOpenFiles": [
    "Gre/填空/GRE填空题.md",
    "Daily/2024-09-08.md",
    "Gre/填空/指代重复.md",
    "托福学习/虎哥口语素材.md",
    "托福学习/写作笔记.md",
    "托福学习/口语大纲.md",
    "托福学习/托福写作模版.md",
    "托福学习/写作句法.md",
    "托福学习/QA.md",
    "托福学习/练习方法.md",
    "托福学习/托福写作语法.md",
    "托福学习/问题.md",
    "托福学习/托福写作.md",
    "托福学习/托福课堂笔记.md",
    "attachment/Pasted image 20240803211829.png",
    "Excalidraw/Drawing 2024-08-03 20.13.58.excalidraw.md",
    "Excalidraw/Drawing 2024-08-03 20.13.59.excalidraw.md",
    "Daily/2024-07-24.md",
    "Daily/2024-07-23.md",
    "Daily/2024-07-20.md",
    "Daily/2024-07-21.md",
    "Daily/2024-07-19.md",
    "Daily/2024-07-18.md",
    "Daily/2024-07-22.md",
    "网课学习笔记/Missing Course MIT.md",
    "Gre/阅读/GRE阅读题型.md",
    "Excalidraw/Drawing 2024-07-16 17.49.56.excalidraw.md",
    "attachment/截屏2023-08-26 11.41.13.png",
    "attachment/截屏2023-08-26 11.24.32.png",
    "attachment/截屏2023-08-19 16.35.51.png",
    "attachment/截屏2023-08-18 15.33.30.png",
    "工具学习/Git/GitCheatSheet_byGeekHour_v1.0.0.pdf",
    "工具学习/Git/Git-Cheet-Sheet-ByGeekHour.png",
    "工具学习/Git",
    "工具学习",
    "网课学习笔记",
    "托福学习",
    "未命名.canvas",
    "面试/笔试",
    "面试",
    "attachment/Pasted image 20240517182832.png",
    "attachment/Pasted image 20240517151159.png",
    "attachment/Pasted image 20240517103147.png",
    "attachment/Pasted image 20240516230615.png",
    "attachment/2023AI期中答案 3.pdf",
    "attachment/2023AI期中答案 2.pdf",
    "attachment/2023AI期中答案 1.pdf",
    "未命名 1.canvas",
    "未命名 3.canvas",
    "未命名 2.canvas"
  ]
}